OOPyGUI/__init__.py
OOPyGUI/core.py
OOPyGUI-1.0.1.dist-info/LICENSE
OOPyGUI-1.0.1.dist-info/METADATA
OOPyGUI-1.0.1.dist-info/WHEEL
OOPyGUI-1.0.1.dist-info/top_level.txt
OOPyGUI-1.0.1.dist-info/RECORD
